{"pageProps":{"countryInfo":{"countryName":"Romania","prefix":"40","description":"Romanian","countryIso":"RO","hasUifn":true,"hasAzTermination":true,"hasVoiceIn":true,"hasVoiceOut":false,"hasSmsIn":false,"hasP2p":false,"hasA2p":false,"hasT38":true,"hasEmergency":false,"hasLocalNumbers":true,"hasNationalNumbers":true,"hasTollFreeNumbers":true,"hasMobileNumbers":false,"hasSharedCostNumbers":false,"prefixes":{"Local":[{"prefix":"344","needsRegistration":true,"hasSms":false,"hasP2p":false,"hasA2p":false,"hasT38":true,"hasVoice":true,"hasVoiceOut":false,"hasEmergency":false,"regionName":null,"cityName":"Ploiesti","fullPrefix":"40-344","areaName":"Ploiesti"},{"prefix":"339","needsRegistration":true,"hasSms":false,"hasP2p":false,"hasA2p":false,"hasT38":true,"hasVoice":true,"hasVoiceOut":false,"hasEmergency":false,"regionName":null,"cityName":"Braila","fullPrefix":"40-339","areaName":"Braila"},{"prefix":"350","needsRegistration":true,"hasSms":false,"hasP2p":false,"hasA2p":false,"hasT38":true,"hasVoice":true,"hasVoiceOut":false,"hasEmergency":false,"regionName":null,"cityName":"Ramnicu Valcea","fullPrefix":"40-350","areaName":"Ramnicu Valcea"},{"prefix":"334","needsRegistration":true,"hasSms":false,"hasP2p":false,"hasA2p":false,"hasT38":true,"hasVoice":true,"hasVoiceOut":false,"hasEmergency":false,"regionName":null,"cityName":"Bacau","fullPrefix":"40-334","areaName":"Bacau"},{"prefix":"357","needsRegistration":true,"hasSms":false,"hasP2p":false,"hasA2p":false,"hasT38":true,"hasVoice":true,"hasVoiceOut":false,"hasEmergency":false,"regionName":null,"cityName":"Arad","fullPrefix":"40-357","areaName":"Arad"},{"prefix":"365","needsRegistration":true,"hasSms":false,"hasP2p":false,"hasA2p":false,"hasT38":true,"hasVoice":true,"hasVoiceOut":false,"hasEmergency":false,"regionName":null,"cityName":"Targu Mures","fullPrefix":"40-365","areaName":"Targu Mures"},{"prefix":"332","needsRegistration":true,"hasSms":false,"hasP2p":false,"hasA2p":false,"hasT38":true,"hasVoice":true,"hasVoiceOut":false,"hasEmergency":false,"regionName":null,"cityName":"Iasi","fullPrefix":"40-332","areaName":"Iasi"},{"prefix":"352","needsRegistration":true,"hasSms":false,"hasP2p":false,"hasA2p":false,"hasT38":true,"hasVoice":true,"hasVoiceOut":false,"hasEmergency":false,"regionName":null,"cityName":"Drobeta-Turnu Severin","fullPrefix":"40-352","areaName":"Drobeta-Turnu Severin"},{"prefix":"338","needsRegistration":true,"hasSms":false,"hasP2p":false,"hasA2p":false,"hasT38":true,"hasVoice":true,"hasVoiceOut":false,"hasEmergency":false,"regionName":null,"cityName":"Buzau","fullPrefix":"40-338","areaName":"Buzau"},{"prefix":"369","needsRegistration":true,"hasSms":false,"hasP2p":false,"hasA2p":false,"hasT38":true,"hasVoice":true,"hasVoiceOut":false,"hasEmergency":false,"regionName":null,"cityName":"Sibiu","fullPrefix":"40-369","areaName":"Sibiu"},{"prefix":"351","needsRegistration":true,"hasSms":false,"hasP2p":false,"hasA2p":false,"hasT38":true,"hasVoice":true,"hasVoiceOut":false,"hasEmergency":false,"regionName":null,"cityName":"Craiova","fullPrefix":"40-351","areaName":"Craiova"},{"prefix":"333","needsRegistration":true,"hasSms":false,"hasP2p":false,"hasA2p":false,"hasT38":true,"hasVoice":true,"hasVoiceOut":false,"hasEmergency":false,"regionName":null,"cityName":"Piatra Neamt","fullPrefix":"40-333","areaName":"Piatra Neamt"},{"prefix":"361","needsRegistration":true,"hasSms":false,"hasP2p":false,"hasA2p":false,"hasT38":true,"hasVoice":true,"hasVoiceOut":false,"hasEmergency":false,"regionName":null,"cityName":"Satu Mare","fullPrefix":"40-361","areaName":"Satu Mare"},{"prefix":"359","needsRegistration":true,"hasSms":false,"hasP2p":false,"hasA2p":false,"hasT38":true,"hasVoice":true,"hasVoiceOut":false,"hasEmergency":false,"regionName":null,"cityName":"Oradea","fullPrefix":"40-359","areaName":"Oradea"},{"prefix":"331","needsRegistration":true,"hasSms":false,"hasP2p":false,"hasA2p":false,"hasT38":true,"hasVoice":true,"hasVoiceOut":false,"hasEmergency":false,"regionName":null,"cityName":"Botosani","fullPrefix":"40-331","areaName":"Botosani"},{"prefix":"348","needsRegistration":true,"hasSms":false,"hasP2p":false,"hasA2p":false,"hasT38":true,"hasVoice":true,"hasVoiceOut":false,"hasEmergency":false,"regionName":null,"cityName":"Pitesti","fullPrefix":"40-348","areaName":"Pitesti"},{"prefix":"356","needsRegistration":true,"hasSms":false,"hasP2p":false,"hasA2p":false,"hasT38":true,"hasVoice":true,"hasVoiceOut":false,"hasEmergency":false,"regionName":null,"cityName":"Timisoara","fullPrefix":"40-356","areaName":"Timisoara"},{"prefix":"364","needsRegistration":true,"hasSms":false,"hasP2p":false,"hasA2p":false,"hasT38":true,"hasVoice":true,"hasVoiceOut":false,"hasEmergency":false,"regionName":null,"cityName":"Cluj-Napoca","fullPrefix":"40-364","areaName":"Cluj-Napoca"},{"prefix":"368","needsRegistration":true,"hasSms":false,"hasP2p":false,"hasA2p":false,"hasT38":true,"hasVoice":true,"hasVoiceOut":false,"hasEmergency":false,"regionName":null,"cityName":"Brasov","fullPrefix":"40-368","areaName":"Brasov"},{"prefix":"330","needsRegistration":true,"hasSms":false,"hasP2p":false,"hasA2p":false,"hasT38":true,"hasVoice":true,"hasVoiceOut":false,"hasEmergency":false,"regionName":null,"cityName":"Suceava","fullPrefix":"40-330","areaName":"Suceava"},{"prefix":"341","needsRegistration":true,"hasSms":false,"hasP2p":false,"hasA2p":false,"hasT38":true,"hasVoice":true,"hasVoiceOut":false,"hasEmergency":false,"regionName":null,"cityName":"Constanta","fullPrefix":"40-341","areaName":"Constanta"},{"prefix":"336","needsRegistration":true,"hasSms":false,"hasP2p":false,"hasA2p":false,"hasT38":true,"hasVoice":true,"hasVoiceOut":false,"hasEmergency":false,"regionName":null,"cityName":"Galati","fullPrefix":"40-336","areaName":"Galati"},{"prefix":"31","needsRegistration":true,"hasSms":false,"hasP2p":false,"hasA2p":false,"hasT38":true,"hasVoice":true,"hasVoiceOut":false,"hasEmergency":false,"regionName":null,"cityName":"Bucharest","fullPrefix":"40-31","areaName":"Bucharest"}],"Toll Free":[{"prefix":"800","needsRegistration":true,"hasSms":false,"hasP2p":false,"hasA2p":false,"hasT38":false,"hasVoice":true,"hasVoiceOut":false,"hasEmergency":false,"regionName":null,"cityName":null,"fullPrefix":"40-800","areaName":"Toll Free"}],"National":[{"prefix":"37","needsRegistration":true,"hasSms":false,"hasP2p":false,"hasA2p":false,"hasT38":false,"hasVoice":true,"hasVoiceOut":false,"hasEmergency":false,"regionName":null,"cityName":null,"fullPrefix":"40-37","areaName":"National"}],"Global":[{"prefix":"800","needsRegistration":true,"hasSms":false,"hasP2p":false,"hasA2p":false,"hasT38":false,"hasVoice":true,"hasVoiceOut":false,"hasEmergency":false,"regionName":null,"cityName":null,"fullPrefix":"800","areaName":"Global"}]},"a2pRequirements":null,"hasPortingNumbers":true,"a2pSupport":{"isAlphanumericSupported":false,"isLongCodeSupported":false},"isRegistrationRequired":true,"portingRequirementsInfo":{"Toll Free":true,"Local":true,"National":true}},"counters":{"countriesCount":92,"prefixesCount":5300}},"__N_SSG":true}