{"pageProps":{"countryInfo":{"countryName":"Vietnam","prefix":"84","description":"Vietnamese","countryIso":"VN","hasUifn":false,"hasAzTermination":true,"hasVoiceIn":true,"hasVoiceOut":false,"hasSmsIn":false,"hasP2p":false,"hasA2p":false,"hasT38":false,"hasEmergency":false,"hasLocalNumbers":true,"hasNationalNumbers":false,"hasTollFreeNumbers":true,"hasMobileNumbers":false,"hasSharedCostNumbers":false,"prefixes":{"Local":[{"prefix":"28","needsRegistration":false,"hasSms":false,"hasP2p":false,"hasA2p":false,"hasT38":false,"hasVoice":true,"hasVoiceOut":false,"hasEmergency":false,"regionName":null,"cityName":"Ho Chi Minh","fullPrefix":"84-28","areaName":"Ho Chi Minh"},{"prefix":"24","needsRegistration":false,"hasSms":false,"hasP2p":false,"hasA2p":false,"hasT38":false,"hasVoice":true,"hasVoiceOut":false,"hasEmergency":false,"regionName":null,"cityName":"Hanoi","fullPrefix":"84-24","areaName":"Hanoi"},{"prefix":"236","needsRegistration":false,"hasSms":false,"hasP2p":false,"hasA2p":false,"hasT38":false,"hasVoice":true,"hasVoiceOut":false,"hasEmergency":false,"regionName":null,"cityName":"Da Nang","fullPrefix":"84-236","areaName":"Da Nang"}],"Toll Free":[{"prefix":"1800","needsRegistration":false,"hasSms":false,"hasP2p":false,"hasA2p":false,"hasT38":false,"hasVoice":true,"hasVoiceOut":false,"hasEmergency":false,"regionName":null,"cityName":null,"fullPrefix":"84-1800","areaName":"Toll Free"}]},"a2pRequirements":null,"hasPortingNumbers":false,"a2pSupport":{"isAlphanumericSupported":false,"isLongCodeSupported":false},"isRegistrationRequired":false,"portingRequirementsInfo":null},"counters":{"countriesCount":92,"prefixesCount":5300}},"__N_SSG":true}